gempaterupdate/__init__.py
quakindo-0.1.4.dist-info/licenses/LICENSE
quakindo-0.1.4.dist-info/METADATA
quakindo-0.1.4.dist-info/WHEEL
quakindo-0.1.4.dist-info/top_level.txt
quakindo-0.1.4.dist-info/RECORD
