Metadata-Version: 2.4
Name: quakindo
Version: 0.1.4
Summary: A simple package to scrape and parse the latest earthquake data from BMKG.
Author-email: Dhimas Primajaya <dhimasprimajaya99@gmail.com>
License:                     GNU GENERAL PUBLIC LICENSE
Project-URL: Homepage, https://github.com/Dhimas-Primajaya/Latest-Earthquake-Update
Project-URL: Repository, https://github.com/Dhimas-Primajaya/Latest-Earthquake-Update
Keywords: bmkg,earthquake,scraper,update
Classifier: Programming Language :: Python :: 3
Classifier: License :: OSI Approved :: GNU General Public License v3 (GPLv3)
Classifier: Operating System :: OS Independent
Classifier: Development Status :: 3 - Alpha
Requires-Python: >=3.8
License-File: LICENSE
Requires-Dist: requests
Requires-Dist: beautifulsoup4
Requires-Dist: lxml
Dynamic: license-file
